mallardetl/__init__.py
mallardetl/error.py
mallardetl/py.typed
mallardetl/tables/__init__.py
mallardetl/tables/dimension.py
mallardetl/tables/fact.py
mallardetl-0.1.2.dist-info/METADATA
mallardetl-0.1.2.dist-info/WHEEL
mallardetl-0.1.2.dist-info/RECORD
